teslajson/__init__.py
teslajson/teslajson.py
teslajson-2.0.0.dist-info/LICENSE
teslajson-2.0.0.dist-info/METADATA
teslajson-2.0.0.dist-info/WHEEL
teslajson-2.0.0.dist-info/top_level.txt
teslajson-2.0.0.dist-info/RECORD
