Metadata-Version: 2.1
Name: teslajson
Version: 2.0.0
Summary: Simple Python class to access the Tesla JSON API
Home-page: https://github.com/gglockner/teslajson
Author: Greg Glockner
Author-email: greg.glockner@gmail.com
License: UNKNOWN
Platform: UNKNOWN
Classifier: Programming Language :: Python :: 3
Classifier: License :: OSI Approved :: MIT License
Classifier: Operating System :: OS Independent
Requires-Dist: requests-oauthlib
